arm_cli/__init__.py
arm_cli/__main__.py
arm_cli/_version.py
arm_cli/cli.py
arm_cli/config.py
arm_cli/settings.py
arm_cli/container/__init__.py
arm_cli/container/container.py
arm_cli/container/readme.md
arm_cli/projects/__init__.py
arm_cli/projects/activate.py
arm_cli/projects/info.py
arm_cli/projects/init.py
arm_cli/projects/list.py
arm_cli/projects/projects.py
arm_cli/projects/remove.py
arm_cli/self/__init__.py
arm_cli/self/self.py
arm_cli/system/__init__.py
arm_cli/system/setup_utils.py
arm_cli/system/system.py
arm_cli/system/shell_scripts/__init__.py
arm_cli/system/shell_scripts/shell_addins.fish
arm_cli/system/shell_scripts/shell_addins.sh
arm_cli/system/shell_scripts/shell_addins.zsh
arm_cli-0.1.10.dist-info/licenses/LICENSE
resources/default_project_config.json
arm_cli-0.1.10.dist-info/METADATA
arm_cli-0.1.10.dist-info/WHEEL
arm_cli-0.1.10.dist-info/entry_points.txt
arm_cli-0.1.10.dist-info/top_level.txt
arm_cli-0.1.10.dist-info/RECORD
