Metadata-Version: 2.4
Name: arm-cli
Version: 0.1.10
Summary: Experimental CLI for deploying robotic applications
Author: Matthew Powelson
License:                                  Apache License
Requires-Python: >=3.8
License-File: LICENSE
Requires-Dist: appdirs
Requires-Dist: beartype
Requires-Dist: click
Requires-Dist: click-completion
Requires-Dist: docker
Requires-Dist: inquirer
Requires-Dist: pydantic
Provides-Extra: dev
Requires-Dist: black==24.8.0; extra == "dev"
Requires-Dist: isort==5.13.2; extra == "dev"
Requires-Dist: pytest; extra == "dev"
Requires-Dist: flake8; extra == "dev"
Requires-Dist: mypy; extra == "dev"
Dynamic: license-file
